Workbook
Name 乙: 計算用!$B$90
Name 冠帯: 計算用!$B$105
Name 逆行: 計算用!$AA$2:$AK$23
Name 建禄: 計算用!$B$106
Name 己: 計算用!$B$94
Name 庚: 計算用!$B$95
Name 甲: 計算用!$B$89
Name 死: 計算用!$B$110
Name 順行: 計算用!$O$2:$Z$23
Name 辛: 計算用!$B$96
Name 壬: 計算用!$B$97
Name 衰: 計算用!$B$108
Name 絶: 計算用!$B$100
Name 胎: 計算用!$B$101
Name 丁: 計算用!$B$92
Name 長生: 計算用!$B$103
Name 帝旺: 計算用!$B$107
Name 病: 計算用!$B$109
Name 丙: 計算用!$B$91
Name 墓: 計算用!$B$111
Name 戊: 計算用!$B$93
Name 養: 計算用!$B$102
Name 沐浴: 計算用!$B$104
Name 癸: 計算用!$B$98

Sheet 計算用
C1: 1 | D1: 2 | E1: 3 | F1: 4 | G1: 5 | H1: 6 | I1: 7 | J1: 8 | K1: 9 | L1: 10 | O1: 順行 | AA1: 逆行
B2: 0 | C2: ０~10 | D2: 11~20 | E2: 21~30 | F2: 31~40 | G2: 41~50 | H2: 51~60 | I2: 61~70 | J2: 71~80 | K2: 81~90 | L2: 91~100 | O2: 甲 | P2: 乙 | Q2: 丙 | R2: 丁 | S2: 戊 | T2: 己 | U2: 庚 | V2: 辛 | W2: 壬 | X2: 癸 | Y2: 甲 | Z2: 乙 | AA2: =INDIRECT(ADDRESS(ROW(),26-(COLUMN()-27))) -> 乙 | AB2: =INDIRECT(ADDRESS(ROW(),26-(COLUMN()-27))) -> 甲 | AC2: =INDIRECT(ADDRESS(ROW(),26-(COLUMN()-27))) -> 癸 | AD2: =INDIRECT(ADDRESS(ROW(),26-(COLUMN()-27))) -> 壬 | AE2: =INDIRECT(ADDRESS(ROW(),26-(COLUMN()-27))) -> 辛 | AF2: =INDIRECT(ADDRESS(ROW(),26-(COLUMN()-27))) -> 庚 | AG2: =INDIRECT(ADDRESS(ROW(),26-(COLUMN()-27))) -> 己 | AH2: =INDIRECT(ADDRESS(ROW(),26-(COLUMN()-27))) -> 戊 | ... AK2: =INDIRECT(ADDRESS(ROW(),26-(COLUMN()-27))) -> 乙 | AM2: 甲 | AN2: 寅
B3: 1 | C3: 0~1 | D3: 2~11 | E3: 12~21 | F3: 22~31 | G3: 32~41 | H3: 42~51 | I3: 52~61 | J3: 62~71 | K3: 72~81 | L3: 82~91 | O3: 乙 | P3: 丙 | Q3: 丁 | R3: 戊 | S3: 己 | T3: 庚 | U3: 辛 | V3: 壬 | W3: 癸 | X3: 甲 | Y3: 乙 | Z3: 丙 | AA3: =INDIRECT(ADDRESS(ROW(),26-(COLUMN()-27))) -> 丙 | AB3: =INDIRECT(ADDRESS(ROW(),26-(COLUMN()-27))) -> 乙 | AC3: =INDIRECT(ADDRESS(ROW(),26-(COLUMN()-27))) -> 甲 | AD3: =INDIRECT(ADDRESS(ROW(),26-(COLUMN()-27))) -> 癸 | AE3: =INDIRECT(ADDRESS(ROW(),26-(COLUMN()-27))) -> 壬 | AF3: =INDIRECT(ADDRESS(ROW(),26-(COLUMN()-27))) -> 辛 | AG3: =INDIRECT(ADDRESS(ROW(),26-(COLUMN()-27))) -> 庚 | AH3: =INDIRECT(ADDRESS(ROW(),26-(COLUMN()-27))) -> 己 | ... AK3: =INDIRECT(ADDRESS(ROW(),26-(COLUMN()-27))) -> 丙 | AM3: 甲 | AN3: 辰
B4: 2 | C4: 0~2 | D4: 3~12 | E4: 13~22 | F4: 23~32 | G4: 33~42 | H4: 43~52 | I4: 53~62 | J4: 63~72 | K4: 73~82 | L4: 83~92 | O4: 丙 | P4: 丁 | Q4: 戊 | R4: 己 | S4: 庚 | T4: 辛 | U4: 壬 | V4: 癸 | W4: 甲 | X4: 乙 | Y4: 丙 | Z4: 丁 | AA4: =INDIRECT(ADDRESS(ROW(),26-(COLUMN()-27))) -> 丁 | AB4: =INDIRECT(ADDRESS(ROW(),26-(COLUMN()-27))) -> 丙 | AC4: =INDIRECT(ADDRESS(ROW(),26-(COLUMN()-27))) -> 乙 | AD4: =INDIRECT(ADDRESS(ROW(),26-(COLUMN()-27))) -> 甲 | AE4: =INDIRECT(ADDRESS(ROW(),26-(COLUMN()-27))) -> 癸 | AF4: =INDIRECT(ADDRESS(ROW(),26-(COLUMN()-27))) -> 壬 | AG4: =INDIRECT(ADDRESS(ROW(),26-(COLUMN()-27))) -> 辛 | AH4: =INDIRECT(ADDRESS(ROW(),26-(COLUMN()-27))) -> 庚 | ... AK4: =INDIRECT(ADDRESS(ROW(),26-(COLUMN()-27))) -> 丁 | AM4: 甲 | AN4: 午
B5: 3 | C5: 0~3 | D5: 4~13 | E5: 14~23 | F5: 24~33 | G5: 34~43 | H5: 44~53 | I5: 54~63 | J5: 64~73 | K5: 74~83 | L5: 84~93 | O5: 丁 | P5: 戊 | Q5: 己 | R5: 庚 | S5: 辛 | T5: 壬 | U5: 癸 | V5: 甲 | W5: 乙 | X5: 丙 | Y5: 丁 | Z5: 戊 | AA5: =INDIRECT(ADDRESS(ROW(),26-(COLUMN()-27))) -> 戊 | AB5: =INDIRECT(ADDRESS(ROW(),26-(COLUMN()-27))) -> 丁 | AC5: =INDIRECT(ADDRESS(ROW(),26-(COLUMN()-27))) -> 丙 | AD5: =INDIRECT(ADDRESS(ROW(),26-(COLUMN()-27))) -> 乙 | AE5: =INDIRECT(ADDRESS(ROW(),26-(COLUMN()-27))) -> 甲 | AF5: =INDIRECT(ADDRESS(ROW(),26-(COLUMN()-27))) -> 癸 | AG5: =INDIRECT(ADDRESS(ROW(),26-(COLUMN()-27))) -> 壬 | AH5: =INDIRECT(ADDRESS(ROW(),26-(COLUMN()-27))) -> 辛 | ... AK5: =INDIRECT(ADDRESS(ROW(),26-(COLUMN()-27))) -> 戊 | AM5: 甲 | AN5: 申
B6: 4 | C6: 0~4 | D6: 5~14 | E6: 15~24 | F6: 25~34 | G6: 35~44 | H6: 45~54 | I6: 55~64 | J6: 65~74 | K6: 75~84 | L6: 85~94 | O6: 戊 | P6: 己 | Q6: 庚 | R6: 辛 | S6: 壬 | T6: 癸 | U6: 甲 | V6: 乙 | W6: 丙 | X6: 丁 | Y6: 戊 | Z6: 己 | AA6: =INDIRECT(ADDRESS(ROW(),26-(COLUMN()-27))) -> 己 | AB6: =INDIRECT(ADDRESS(ROW(),26-(COLUMN()-27))) -> 戊 | AC6: =INDIRECT(ADDRESS(ROW(),26-(COLUMN()-27))) -> 丁 | AD6: =INDIRECT(ADDRESS(ROW(),26-(COLUMN()-27))) -> 丙 | AE6: =INDIRECT(ADDRESS(ROW(),26-(COLUMN()-27))) -> 乙 | AF6: =INDIRECT(ADDRESS(ROW(),26-(COLUMN()-27))) -> 甲 | AG6: =INDIRECT(ADDRESS(ROW(),26-(COLUMN()-27))) -> 癸 | AH6: =INDIRECT(ADDRESS(ROW(),26-(COLUMN()-27))) -> 壬 | ... AK6: =INDIRECT(ADDRESS(ROW(),26-(COLUMN()-27))) -> 己 | AM6: 甲 | AN6: 戌
B7: 5 | C7: 0~5 | D7: 6~15 | E7: 16~25 | F7: 26~35 | G7: 36~45 | H7: 46~55 | I7: 56~65 | J7: 66~75 | K7: 76~85 | L7: 86~95 | O7: 己 | P7: 庚 | Q7: 辛 | R7: 壬 | S7: 癸 | T7: 甲 | U7: 乙 | V7: 丙 | W7: 丁 | X7: 戊 | Y7: 己 | Z7: 庚 | AA7: =INDIRECT(ADDRESS(ROW(),26-(COLUMN()-27))) -> 庚 | AB7: =INDIRECT(ADDRESS(ROW(),26-(COLUMN()-27))) -> 己 | AC7: =INDIRECT(ADDRESS(ROW(),26-(COLUMN()-27))) -> 戊 | AD7: =INDIRECT(ADDRESS(ROW(),26-(COLUMN()-27))) -> 丁 | AE7: =INDIRECT(ADDRESS(ROW(),26-(COLUMN()-27))) -> 丙 | AF7: =INDIRECT(ADDRESS(ROW(),26-(COLUMN()-27))) -> 乙 | AG7: =INDIRECT(ADDRESS(ROW(),26-(COLUMN()-27))) -> 甲 | AH7: =INDIRECT(ADDRESS(ROW(),26-(COLUMN()-27))) -> 癸 | ... AK7: =INDIRECT(ADDRESS(ROW(),26-(COLUMN()-27))) -> 庚 | AM7: 甲 | AN7: 子
B8: 6 | C8: 0~6 | D8: 7~16 | E8: 17~26 | F8: 27~36 | G8: 37~46 | H8: 47~56 | I8: 57~66 | J8: 67~76 | K8: 77~86 | L8: 87~96 | O8: 庚 | P8: 辛 | Q8: 壬 | R8: 癸 | S8: 甲 | T8: 乙 | U8: 丙 | V8: 丁 | W8: 戊 | X8: 己 | Y8: 庚 | Z8: 辛 | AA8: =INDIRECT(ADDRESS(ROW(),26-(COLUMN()-27))) -> 辛 | AB8: =INDIRECT(ADDRESS(ROW(),26-(COLUMN()-27))) -> 庚 | AC8: =INDIRECT(ADDRESS(ROW(),26-(COLUMN()-27))) -> 己 | AD8: =INDIRECT(ADDRESS(ROW(),26-(COLUMN()-27))) -> 戊 | AE8: =INDIRECT(ADDRESS(ROW(),26-(COLUMN()-27))) -> 丁 | AF8: =INDIRECT(ADDRESS(ROW(),26-(COLUMN()-27))) -> 丙 | AG8: =INDIRECT(ADDRESS(ROW(),26-(COLUMN()-27))) -> 乙 | AH8: =INDIRECT(ADDRESS(ROW(),26-(COLUMN()-27))) -> 甲 | ... AK8: =INDIRECT(ADDRESS(ROW(),26-(COLUMN()-27))) -> 辛 | AM8: 乙 | AN8: 卯
B9: 7 | C9: 0~7 | D9: 8~17 | E9: 18~27 | F9: 28~37 | G9: 38~47 | H9: 48~57 | I9: 58~67 | J9: 68~77 | K9: 78~87 | L9: 88~97 | O9: 辛 | P9: 壬 | Q9: 癸 | R9: 甲 | S9: 乙 | T9: 丙 | U9: 丁 | V9: 戊 | W9: 己 | X9: 庚 | Y9: 辛 | Z9: 壬 | AA9: =INDIRECT(ADDRESS(ROW(),26-(COLUMN()-27))) -> 壬 | AB9: =INDIRECT(ADDRESS(ROW(),26-(COLUMN()-27))) -> 辛 | AC9: =INDIRECT(ADDRESS(ROW(),26-(COLUMN()-27))) -> 庚 | AD9: =INDIRECT(ADDRESS(ROW(),26-(COLUMN()-27))) -> 己 | AE9: =INDIRECT(ADDRESS(ROW(),26-(COLUMN()-27))) -> 戊 | AF9: =INDIRECT(ADDRESS(ROW(),26-(COLUMN()-27))) -> 丁 | AG9: =INDIRECT(ADDRESS(ROW(),26-(COLUMN()-27))) -> 丙 | AH9: =INDIRECT(ADDRESS(ROW(),26-(COLUMN()-27))) -> 乙 | ... AK9: =INDIRECT(ADDRESS(ROW(),26-(COLUMN()-27))) -> 壬 | AM9: 乙 | AN9: 巳
B10: 8 | C10: 0~8 | D10: 9~18 | E10: 19~28 | F10: 29~38 | G10: 39~48 | H10: 49~58 | I10: 59~68 | J10: 69~78 | K10: 79~88 | L10: 89~98 | O10: 壬 | P10: 癸 | Q10: 甲 | R10: 乙 | S10: 丙 | T10: 丁 | U10: 戊 | V10: 己 | W10: 庚 | X10: 辛 | Y10: 壬 | Z10: 癸 | AA10: =INDIRECT(ADDRESS(ROW(),26-(COLUMN()-27))) -> 癸 | AB10: =INDIRECT(ADDRESS(ROW(),26-(COLUMN()-27))) -> 壬 | AC10: =INDIRECT(ADDRESS(ROW(),26-(COLUMN()-27))) -> 辛 | AD10: =INDIRECT(ADDRESS(ROW(),26-(COLUMN()-27))) -> 庚 | AE10: =INDIRECT(ADDRESS(ROW(),26-(COLUMN()-27))) -> 己 | AF10: =INDIRECT(ADDRESS(ROW(),26-(COLUMN()-27))) -> 戊 | AG10: =INDIRECT(ADDRESS(ROW(),26-(COLUMN()-27))) -> 丁 | AH10: =INDIRECT(ADDRESS(ROW(),26-(COLUMN()-27))) -> 丙 | ... AK10: =INDIRECT(ADDRESS(ROW(),26-(COLUMN()-27))) -> 癸 | AM10: 乙 | AN10: 未
B11: 9 | C11: 0~9 | D11: 10~19 | E11: 20~29 | F11: 30~39 | G11: 40~49 | H11: 50~59 | I11: 60~69 | J11: 70~79 | K11: 80~89 | L11: 90~99 | O11: 癸 | P11: 甲 | Q11: 乙 | R11: 丙 | S11: 丁 | T11: 戊 | U11: 己 | V11: 庚 | W11: 辛 | X11: 壬 | Y11: 癸 | Z11: 甲 | AA11: =INDIRECT(ADDRESS(ROW(),26-(COLUMN()-27))) -> 甲 | AB11: =INDIRECT(ADDRESS(ROW(),26-(COLUMN()-27))) -> 癸 | AC11: =INDIRECT(ADDRESS(ROW(),26-(COLUMN()-27))) -> 壬 | AD11: =INDIRECT(ADDRESS(ROW(),26-(COLUMN()-27))) -> 辛 | AE11: =INDIRECT(ADDRESS(ROW(),26-(COLUMN()-27))) -> 庚 | AF11: =INDIRECT(ADDRESS(ROW(),26-(COLUMN()-27))) -> 己 | AG11: =INDIRECT(ADDRESS(ROW(),26-(COLUMN()-27))) -> 戊 | AH11: =INDIRECT(ADDRESS(ROW(),26-(COLUMN()-27))) -> 丁 | ... AK11: =INDIRECT(ADDRESS(ROW(),26-(COLUMN()-27))) -> 甲 | AM11: 乙 | AN11: 酉
B12: 10 | C12: 0 | D12: 1~10 | E12: 11~20 | F12: 21~30 | G12: 31~40 | H12: 41~50 | I12: 51~60 | J12: 61~70 | K12: 71~80 | L12: 81~90 | O12: 子 | P12: 丑 | Q12: 寅 | R12: 卯 | S12: 辰 | T12: 巳 | U12: 午 | V12: 未 | W12: 申 | X12: 酉 | Y12: 戌 | Z12: 亥 | AA12: =INDIRECT(ADDRESS(ROW(),26-(COLUMN()-27))) -> 亥 | AB12: =INDIRECT(ADDRESS(ROW(),26-(COLUMN()-27))) -> 戌 | AC12: =INDIRECT(ADDRESS(ROW(),26-(COLUMN()-27))) -> 酉 | AD12: =INDIRECT(ADDRESS(ROW(),26-(COLUMN()-27))) -> 申 | AE12: =INDIRECT(ADDRESS(ROW(),26-(COLUMN()-27))) -> 未 | AF12: =INDIRECT(ADDRESS(ROW(),26-(COLUMN()-27))) -> 午 | AG12: =INDIRECT(ADDRESS(ROW(),26-(COLUMN()-27))) -> 巳 | AH12: =INDIRECT(ADDRESS(ROW(),26-(COLUMN()-27))) -> 辰 | ... AK12: =INDIRECT(ADDRESS(ROW(),26-(COLUMN()-27))) -> 丑 | AM12: 乙 | AN12: 亥
C13: 比肩 | D13: 劫財 | E13: 食神 | F13: 傷官 | G13: 偏財 | H13: 正財 | I13: 偏官 | J13: 正官 | K13: 偏印 | L13: 印綬 | O13: 丑 | P13: 寅 | Q13: 卯 | R13: 辰 | S13: 巳 | T13: 午 | U13: 未 | V13: 申 | W13: 酉 | X13: 戌 | Y13: 亥 | Z13: 子 | AA13: =INDIRECT(ADDRESS(ROW(),26-(COLUMN()-27))) -> 子 | AB13: =INDIRECT(ADDRESS(ROW(),26-(COLUMN()-27))) -> 亥 | AC13: =INDIRECT(ADDRESS(ROW(),26-(COLUMN()-27))) -> 戌 | AD13: =INDIRECT(ADDRESS(ROW(),26-(COLUMN()-27))) -> 酉 | AE13: =INDIRECT(ADDRESS(ROW(),26-(COLUMN()-27))) -> 申 | AF13: =INDIRECT(ADDRESS(ROW(),26-(COLUMN()-27))) -> 未 | AG13: =INDIRECT(ADDRESS(ROW(),26-(COLUMN()-27))) -> 午 | AH13: =INDIRECT(ADDRESS(ROW(),26-(COLUMN()-27))) -> 巳 | ... AK13: =INDIRECT(ADDRESS(ROW(),26-(COLUMN()-27))) -> 寅 | AM13: 乙 | AN13: 丑
C14: 活動 | D14: 浪費 | E14: 調整 | F14: 焦燥 | G14: 投資 | H14: 成果 | I14: 転換 | J14: 完結 | K14: 整理 | L14: 学習 | O14: 寅 | P14: 卯 | Q14: 辰 | R14: 巳 | S14: 午 | T14: 未 | U14: 申 | V14: 酉 | W14: 戌 | X14: 亥 | Y14: 子 | Z14: 丑 | AA14: =INDIRECT(ADDRESS(ROW(),26-(COLUMN()-27))) -> 丑 | AB14: =INDIRECT(ADDRESS(ROW(),26-(COLUMN()-27))) -> 子 | AC14: =INDIRECT(ADDRESS(ROW(),26-(COLUMN()-27))) -> 亥 | AD14: =INDIRECT(ADDRESS(ROW(),26-(COLUMN()-27))) -> 戌 | AE14: =INDIRECT(ADDRESS(ROW(),26-(COLUMN()-27))) -> 酉 | AF14: =INDIRECT(ADDRESS(ROW(),26-(COLUMN()-27))) -> 申 | AG14: =INDIRECT(ADDRESS(ROW(),26-(COLUMN()-27))) -> 未 | AH14: =INDIRECT(ADDRESS(ROW(),26-(COLUMN()-27))) -> 午 | ... AK14: =INDIRECT(ADDRESS(ROW(),26-(COLUMN()-27))) -> 卯 | AM14: 丙 | AN14: 辰
B15: 日干 | C15: 甲 | D15: 乙 | E15: 丙 | F15: 丁 | G15: 戊 | H15: 己 | I15: 庚 | J15: 辛 | K15: 壬 | L15: 癸 | O15: 卯 | P15: 辰 | Q15: 巳 | R15: 午 | S15: 未 | T15: 申 | U15: 酉 | V15: 戌 | W15: 亥 | X15: 子 | Y15: 丑 | Z15: 寅 | AA15: =INDIRECT(ADDRESS(ROW(),26-(COLUMN()-27))) -> 寅 | AB15: =INDIRECT(ADDRESS(ROW(),26-(COLUMN()-27))) -> 丑 | AC15: =INDIRECT(ADDRESS(ROW(),26-(COLUMN()-27))) -> 子 | AD15: =INDIRECT(ADDRESS(ROW(),26-(COLUMN()-27))) -> 亥 | AE15: =INDIRECT(ADDRESS(ROW(),26-(COLUMN()-27))) -> 戌 | AF15: =INDIRECT(ADDRESS(ROW(),26-(COLUMN()-27))) -> 酉 | AG15: =INDIRECT(ADDRESS(ROW(),26-(COLUMN()-27))) -> 申 | AH15: =INDIRECT(ADDRESS(ROW(),26-(COLUMN()-27))) -> 未 | ... AK15: =INDIRECT(ADDRESS(ROW(),26-(COLUMN()-27))) -> 辰 | AM15: 丙 | AN15: 午
B16: 甲 | C16: 比肩 | D16: 劫財 | E16: 食神 | F16: 傷官 | G16: 偏財 | H16: 正財 | I16: 偏官 | J16: 正官 | K16: 偏印 | L16: 印綬 | O16: 辰 | P16: 巳 | Q16: 午 | R16: 未 | S16: 申 | T16: 酉 | U16: 戌 | V16: 亥 | W16: 子 | X16: 丑 | Y16: 寅 | Z16: 卯 | AA16: =INDIRECT(ADDRESS(ROW(),26-(COLUMN()-27))) -> 卯 | AB16: =INDIRECT(ADDRESS(ROW(),26-(COLUMN()-27))) -> 寅 | AC16: =INDIRECT(ADDRESS(ROW(),26-(COLUMN()-27))) -> 丑 | AD16: =INDIRECT(ADDRESS(ROW(),26-(COLUMN()-27))) -> 子 | AE16: =INDIRECT(ADDRESS(ROW(),26-(COLUMN()-27))) -> 亥 | AF16: =INDIRECT(ADDRESS(ROW(),26-(COLUMN()-27))) -> 戌 | AG16: =INDIRECT(ADDRESS(ROW(),26-(COLUMN()-27))) -> 酉 | AH16: =INDIRECT(ADDRESS(ROW(),26-(COLUMN()-27))) -> 申 | ... AK16: =INDIRECT(ADDRESS(ROW(),26-(COLUMN()-27))) -> 巳 | AM16: 丙 | AN16: 申
B17: 乙 | C17: 劫財 | D17: 比肩 | E17: 傷官 | F17: 食神 | G17: 正財 | H17: 偏財 | I17: 正官 | J17: 偏官 | K17: 印綬 | L17: 偏印 | O17: 巳 | P17: 午 | Q17: 未 | R17: 申 | S17: 酉 | T17: 戌 | U17: 亥 | V17: 子 | W17: 丑 | X17: 寅 | Y17: 卯 | Z17: 辰 | AA17: =INDIRECT(ADDRESS(ROW(),26-(COLUMN()-27))) -> 辰 | AB17: =INDIRECT(ADDRESS(ROW(),26-(COLUMN()-27))) -> 卯 | AC17: =INDIRECT(ADDRESS(ROW(),26-(COLUMN()-27))) -> 寅 | AD17: =INDIRECT(ADDRESS(ROW(),26-(COLUMN()-27))) -> 丑 | AE17: =INDIRECT(ADDRESS(ROW(),26-(COLUMN()-27))) -> 子 | AF17: =INDIRECT(ADDRESS(ROW(),26-(COLUMN()-27))) -> 亥 | AG17: =INDIRECT(ADDRESS(ROW(),26-(COLUMN()-27))) -> 戌 | AH17: =INDIRECT(ADDRESS(ROW(),26-(COLUMN()-27))) -> 酉 | ... AK17: =INDIRECT(ADDRESS(ROW(),26-(COLUMN()-27))) -> 午 | AM17: 丙 | AN17: 戌
B18: 丙 | C18: 偏印 | D18: 印綬 | E18: 比肩 | F18: 劫財 | G18: 食神 | H18: 傷官 | I18: 偏財 | J18: 正財 | K18: 偏官 | L18: 正官 | O18: 午 | P18: 未 | Q18: 申 | R18: 酉 | S18: 戌 | T18: 亥 | U18: 子 | V18: 丑 | W18: 寅 | X18: 卯 | Y18: 辰 | Z18: 巳 | AA18: =INDIRECT(ADDRESS(ROW(),26-(COLUMN()-27))) -> 巳 | AB18: =INDIRECT(ADDRESS(ROW(),26-(COLUMN()-27))) -> 辰 | AC18: =INDIRECT(ADDRESS(ROW(),26-(COLUMN()-27))) -> 卯 | AD18: =INDIRECT(ADDRESS(ROW(),26-(COLUMN()-27))) -> 寅 | AE18: =INDIRECT(ADDRESS(ROW(),26-(COLUMN()-27))) -> 丑 | AF18: =INDIRECT(ADDRESS(ROW(),26-(COLUMN()-27))) -> 子 | AG18: =INDIRECT(ADDRESS(ROW(),26-(COLUMN()-27))) -> 亥 | AH18: =INDIRECT(ADDRESS(ROW(),26-(COLUMN()-27))) -> 戌 | ... AK18: =INDIRECT(ADDRESS(ROW(),26-(COLUMN()-27))) -> 未 | AM18: 丙 | AN18: 子
B19: 丁 | C19: 印綬 | D19: 偏印 | E19: 劫財 | F19: 比肩 | G19: 傷官 | H19: 食神 | I19: 正財 | J19: 偏財 | K19: 正官 | L19: 偏官 | O19: 未 | P19: 申 | Q19: 酉 | R19: 戌 | S19: 亥 | T19: 子 | U19: 丑 | V19: 寅 | W19: 卯 | X19: 辰 | Y19: 巳 | Z19: 午 | AA19: =INDIRECT(ADDRESS(ROW(),26-(COLUMN()-27))) -> 午 | AB19: =INDIRECT(ADDRESS(ROW(),26-(COLUMN()-27))) -> 巳 | AC19: =INDIRECT(ADDRESS(ROW(),26-(COLUMN()-27))) -> 辰 | AD19: =INDIRECT(ADDRESS(ROW(),26-(COLUMN()-27))) -> 卯 | AE19: =INDIRECT(ADDRESS(ROW(),26-(COLUMN()-27))) -> 寅 | AF19: =INDIRECT(ADDRESS(ROW(),26-(COLUMN()-27))) -> 丑 | AG19: =INDIRECT(ADDRESS(ROW(),26-(COLUMN()-27))) -> 子 | AH19: =INDIRECT(ADDRESS(ROW(),26-(COLUMN()-27))) -> 亥 | ... AK19: =INDIRECT(ADDRESS(ROW(),26-(COLUMN()-27))) -> 申 | AM19: 丙 | AN19: 寅
B20: 戊 | C20: 偏官 | D20: 正官 | E20: 偏印 | F20: 印綬 | G20: 比肩 | H20: 劫財 | I20: 食神 | J20: 傷官 | K20: 偏財 | L20: 正財 | O20: 申 | P20: 酉 | Q20: 戌 | R20: 亥 | S20: 子 | T20: 丑 | U20: 寅 | V20: 卯 | W20: 辰 | X20: 巳 | Y20: 午 | Z20: 未 | AA20: =INDIRECT(ADDRESS(ROW(),26-(COLUMN()-27))) -> 未 | AB20: =INDIRECT(ADDRESS(ROW(),26-(COLUMN()-27))) -> 午 | AC20: =INDIRECT(ADDRESS(ROW(),26-(COLUMN()-27))) -> 巳 | AD20: =INDIRECT(ADDRESS(ROW(),26-(COLUMN()-27))) -> 辰 | AE20: =INDIRECT(ADDRESS(ROW(),26-(COLUMN()-27))) -> 卯 | AF20: =INDIRECT(ADDRESS(ROW(),26-(COLUMN()-27))) -> 寅 | AG20: =INDIRECT(ADDRESS(ROW(),26-(COLUMN()-27))) -> 丑 | AH20: =INDIRECT(ADDRESS(ROW(),26-(COLUMN()-27))) -> 子 | ... AK20: =INDIRECT(ADDRESS(ROW(),26-(COLUMN()-27))) -> 酉 | AM20: 丁 | AN20: 巳
B21: 己 | C21: 正官 | D21: 偏官 | E21: 印綬 | F21: 偏印 | G21: 劫財 | H21: 比肩 | I21: 傷官 | J21: 食神 | K21: 正財 | L21: 偏財 | O21: 酉 | P21: 戌 | Q21: 亥 | R21: 子 | S21: 丑 | T21: 寅 | U21: 卯 | V21: 辰 | W21: 巳 | X21: 午 | Y21: 未 | Z21: 申 | AA21: =INDIRECT(ADDRESS(ROW(),26-(COLUMN()-27))) -> 申 | AB21: =INDIRECT(ADDRESS(ROW(),26-(COLUMN()-27))) -> 未 | AC21: =INDIRECT(ADDRESS(ROW(),26-(COLUMN()-27))) -> 午 | AD21: =INDIRECT(ADDRESS(ROW(),26-(COLUMN()-27))) -> 巳 | AE21: =INDIRECT(ADDRESS(ROW(),26-(COLUMN()-27))) -> 辰 | AF21: =INDIRECT(ADDRESS(ROW(),26-(COLUMN()-27))) -> 卯 | AG21: =INDIRECT(ADDRESS(ROW(),26-(COLUMN()-27))) -> 寅 | AH21: =INDIRECT(ADDRESS(ROW(),26-(COLUMN()-27))) -> 丑 | ... AK21: =INDIRECT(ADDRESS(ROW(),26-(COLUMN()-27))) -> 戌 | AM21: 丁 | AN21: 未
B22: 庚 | C22: 偏財 | D22: 正財 | E22: 偏官 | F22: 正官 | G22: 偏印 | H22: 印綬 | I22: 比肩 | J22: 劫財 | K22: 食神 | L22: 傷官 | O22: 戌 | P22: 亥 | Q22: 子 | R22: 丑 | S22: 寅 | T22: 卯 | U22: 辰 | V22: 巳 | W22: 午 | X22: 未 | Y22: 申 | Z22: 酉 | AA22: =INDIRECT(ADDRESS(ROW(),26-(COLUMN()-27))) -> 酉 | AB22: =INDIRECT(ADDRESS(ROW(),26-(COLUMN()-27))) -> 申 | AC22: =INDIRECT(ADDRESS(ROW(),26-(COLUMN()-27))) -> 未 | AD22: =INDIRECT(ADDRESS(ROW(),26-(COLUMN()-27))) -> 午 | AE22: =INDIRECT(ADDRESS(ROW(),26-(COLUMN()-27))) -> 巳 | AF22: =INDIRECT(ADDRESS(ROW(),26-(COLUMN()-27))) -> 辰 | AG22: =INDIRECT(ADDRESS(ROW(),26-(COLUMN()-27))) -> 卯 | AH22: =INDIRECT(ADDRESS(ROW(),26-(COLUMN()-27))) -> 寅 | ... AK22: =INDIRECT(ADDRESS(ROW(),26-(COLUMN()-27))) -> 亥 | AM22: 丁 | AN22: 酉
B23: 辛 | C23: 正財 | D23: 偏財 | E23: 正官 | F23: 偏官 | G23: 印綬 | H23: 偏印 | I23: 劫財 | J23: 比肩 | K23: 傷官 | L23: 食神 | O23: 亥 | P23: 子 | Q23: 丑 | R23: 寅 | S23: 卯 | T23: 辰 | U23: 巳 | V23: 午 | W23: 未 | X23: 申 | Y23: 酉 | Z23: 戌 | AA23: =INDIRECT(ADDRESS(ROW(),26-(COLUMN()-27))) -> 戌 | AB23: =INDIRECT(ADDRESS(ROW(),26-(COLUMN()-27))) -> 酉 | AC23: =INDIRECT(ADDRESS(ROW(),26-(COLUMN()-27))) -> 申 | AD23: =INDIRECT(ADDRESS(ROW(),26-(COLUMN()-27))) -> 未 | AE23: =INDIRECT(ADDRESS(ROW(),26-(COLUMN()-27))) -> 午 | AF23: =INDIRECT(ADDRESS(ROW(),26-(COLUMN()-27))) -> 巳 | AG23: =INDIRECT(ADDRESS(ROW(),26-(COLUMN()-27))) -> 辰 | AH23: =INDIRECT(ADDRESS(ROW(),26-(COLUMN()-27))) -> 卯 | ... AK23: =INDIRECT(ADDRESS(ROW(),26-(COLUMN()-27))) -> 子 | AM23: 丁 | AN23: 亥
B24: 壬 | C24: 食神 | D24: 傷官 | E24: 偏財 | F24: 正財 | G24: 偏官 | H24: 正官 | I24: 偏印 | J24: 印綬 | K24: 比肩 | L24: 劫財 | AM24: 丁 | AN24: 丑
B25: 癸 | C25: 傷官 | D25: 食神 | E25: 正財 | F25: 偏財 | G25: 正官 | H25: 偏官 | I25: 印綬 | J25: 偏印 | K25: 劫財 | L25: 比肩 | AM25: 丁 | AN25: 卯
AM26: 戊 | AN26: 午
C27: 子 | D27: 丑 | E27: 寅 | F27: 卯 | G27: 辰 | H27: 巳 | I27: 午 | J27: 未 | K27: 申 | L27: 酉 | M27: 戌 | N27: 亥 | AM27: 戊 | AN27: 申
B28: 甲 | C28: 沐浴 | D28: 冠帯 | E28: 建禄 | F28: 帝旺 | G28: 衰 | H28: 病 | I28: 死 | J28: 墓 | K28: 絶 | L28: 胎 | M28: 養 | N28: 長生 | P28: 甲 | Q28: 木 | S28: 木 | T28: 火 | U28: 土 | V28: 金 | W28: 水 | AM28: 戊 | AN28: 戌
B29: 乙 | C29: 病 | D29: 衰 | E29: 帝旺 | F29: 建禄 | G29: 冠帯 | H29: 沐浴 | I29: 長生 | J29: 養 | K29: 胎 | L29: 絶 | M29: 墓 | N29: 死 | P29: 乙 | Q29: 木 | S29: 火 | T29: 土 | U29: 金 | V29: 水 | W29: 木 | AM29: 戊 | AN29: 子
B30: 丙 | C30: 胎 | D30: 養 | E30: 長生 | F30: 沐浴 | G30: 冠帯 | H30: 建禄 | I30: 帝旺 | J30: 衰 | K30: 病 | L30: 死 | M30: 墓 | N30: 絶 | P30: 丙 | Q30: 火 | S30: 土 | T30: 金 | U30: 水 | V30: 木 | W30: 火 | AM30: 戊 | AN30: 寅
B31: 丁 | C31: 絶 | D31: 墓 | E31: 死 | F31: 病 | G31: 衰 | H31: 帝旺 | I31: 建禄 | J31: 冠帯 | K31: 沐浴 | L31: 長生 | M31: 養 | N31: 胎 | P31: 丁 | Q31: 火 | S31: 金 | T31: 水 | U31: 木 | V31: 火 | W31: 土 | AM31: 戊 | AN31: 辰
B32: 戊 | C32: 胎 | D32: 養 | E32: 長生 | F32: 沐浴 | G32: 冠帯 | H32: 建禄 | I32: 帝旺 | J32: 衰 | K32: 病 | L32: 死 | M32: 墓 | N32: 絶 | P32: 戊 | Q32: 土 | S32: 水 | T32: 木 | U32: 火 | V32: 土 | W32: 金 | AM32: 己 | AN32: 未
B33: 己 | C33: 絶 | D33: 墓 | E33: 死 | F33: 病 | G33: 衰 | H33: 帝旺 | I33: 建禄 | J33: 冠帯 | K33: 沐浴 | L33: 長生 | M33: 養 | N33: 胎 | P33: 己 | Q33: 土 | AM33: 己 | AN33: 酉
B34: 庚 | C34: 死 | D34: 墓 | E34: 絶 | F34: 胎 | G34: 養 | H34: 長生 | I34: 沐浴 | J34: 冠帯 | K34: 建禄 | L34: 帝旺 | M34: 衰 | N34: 病 | P34: 庚 | Q34: 金 | AM34: 己 | AN34: 亥
B35: 辛 | C35: 長生 | D35: 養 | E35: 胎 | F35: 絶 | G35: 墓 | H35: 死 | I35: 病 | J35: 衰 | K35: 帝旺 | L35: 建禄 | M35: 冠帯 | N35: 沐浴 | P35: 辛 | Q35: 金 | AM35: 己 | AN35: 丑
B36: 壬 | C36: 帝旺 | D36: 衰 | E36: 病 | F36: 死 | G36: 墓 | H36: 絶 | I36: 胎 | J36: 養 | K36: 長生 | L36: 沐浴 | M36: 冠帯 | N36: 建禄 | P36: 壬 | Q36: 水 | AM36: 己 | AN36: 卯
B37: 癸 | C37: 建禄 | D37: 冠帯 | E37: 沐浴 | F37: 長生 | G37: 養 | H37: 胎 | I37: 絶 | J37: 墓 | K37: 死 | L37: 病 | M37: 衰 | N37: 帝旺 | P37: 癸 | Q37: 水 | AM37: 己 | AN37: 巳
C38: 長生 | D38: 沐浴 | E38: 冠帯 | F38: 建禄 | G38: 帝旺 | H38: 衰 | I38: 病 | J38: 死 | K38: 墓 | L38: 絶 | M38: 胎 | N38: 養 | AM38: 庚 | AN38: 申
B39: 比肩 | C39: 活動 | D39: 亥 | E39: 戌 | F39: 酉 | G39: 申 | H39: 未 | I39: 午 | J39: 巳 | K39: 辰 | L39: 卯 | M39: 寅 | N39: 丑 | O39: 子 | P39: 比肩 | Q39: 自我の星 | R39: 守備本能 | S39: 社会や自分のルールを守って生きた方が才能が開花しやすい。 | T39: 【生一本なマイペース人間】【自分の意見を押し通しイエスと言わせたい】 | U39: 独立心旺盛で、自分の信じることを主張する。負けず嫌いなので、競争心や闘争心が強い。一歩一歩頑張る。自分で何かをしたい。これだと信じた道を貫いていく。早く自分のレールを見つける事が成功の秘訣。 | AM39: 庚 | AN39: 戌
B40: 劫財 | C40: 浪費 | D40: 癸 | E40: 壬 | F40: 辛 | G40: 庚 | H40: 己 | I40: 戊 | J40: 丁 | K40: 丙 | L40: 乙 | M40: 甲 | P40: 劫財 | Q40: 自我の星 | R40: 守備本能 | S40: 社会や自分のルールを守って生きた方が才能が開花しやすい。 | T40: 【社交的な頑張り屋】【人の意見を聞きながら自分の意見にイエスと言わせたい】 | U40: 表面は温和だが妥協はしない。負けず嫌い。人との駆け引きがうまい。人当たりがよく、外での評判はいいが、家族ではワンマンで口うるさくなりがち。外では頑張れる。組織をまとめるリーダータイプ。 | AM40: 庚 | AN40: 子
B41: 食神 | C41: 調整 | P41: 食神 | Q41: 表現の星 | R41: 伝達本能 | S41: 情報を発信していく方が才能が開花する。楽しいを発見していく。 | T41: 【ユーモアあふれるゆとり人間】【B級グルメなら食神にお任せ】 | U41: おおらかでさっぱりしているが、こだわりが強いところもある。ユーモアがあり、人懐っこいため好感が持たれる。表現力豊かで、芸術的才能を現し、多芸多趣味で何でもできる。 | AM41: 庚 | AN41: 寅
B42: 傷官 | C42: 焦燥 | P42: 傷官 | Q42: 表現の星 | R42: 伝達本能 | S42: 情報を発信していく方が才能が開花する。楽しいを発見していく。 | T42: 【直感鋭い芸術人間】【妄想族】 | U42: 一人の時間が才能を伸ばす（完全に一人ではなく、まんがの世界に入り込むなど）。直観力や観察力はあるが、自分の考えに固執し協調性に乏しい面も。敵味方がはっきりしている。正義感も強い。 | AM42: 庚 | AN42: 辰
B43: 偏財 | C43: 投資 | P43: 偏財 | Q43: 財の星 | R43: 魅力本能 | S43: 魅力ある生き方がしたい | T43: 【世話好きな現実人間】【お金使い粗い№１】【自分よりも他人の金銭運用が巧み】 | U43: 金銭感覚が一人の時と大勢の時と違う。融通が利く、物事に対して割り切りが早い。いつも周りに人が集まる。奉仕をし、感謝される派手な生き方。お金に困りにくいが、あまり身につかない。 | AM43: 庚 | AN43: 午
B44: 正財 | C44: 成果 | P44: 正財 | Q44: 財の星 | R44: 魅力本能 | S44: 魅力ある生き方がしたい | T44: 【常識的なコツコツ人間】【自分の金銭運用が巧み】 | U44: 真面目で曲がったことが嫌い。几帳面・勤勉実行型・慎重で用心深く貯蓄上手。安定が魅力。常に常識的でありたいと望んでいる。キャリアと信頼を重視。現金主義な方も多い。 | AM44: 辛 | AN44: 酉
B45: 偏官 | C45: 転換 | P45: 偏官 | Q45: 地位の星 | R45: 攻撃本能 | S45: 何か目標を決める | T45: 【知性と反逆の行動人間】 | U45: 正直で一本気な上に、良い意味で単純です。涙もろく人を疑うことを知らないお人好し。「俺についてこい！」といった親分肌に憧れる。 | AM45: 辛 | AN45: 亥
B46: 正官 | C46: 完結 | P46: 正官 | Q46: 地位の星 | R46: 攻撃本能 | S46: 何か目標を決める | T46: 【信頼と気品の真面目人間】 | U46: 自他ともに厳しい。見栄っ張りなところがあり交際範囲も広く、金遣いは激しい(偏財の次)みっともないことはしたくない。優等生タイプ。 | AM46: 辛 | AN46: 丑
B47: 偏印 | C47: 整理 | P47: 偏印 | Q47: 知性の星 | R47: 習得本能 | S47: 常にインプットし、同時にアウトプットもし続ける。 | T47: 【個性的で頑固な冒険家】 | U47: 知的好奇心が強く、機敏、多感、多才で受けたものを変化させて実現する。常識や伝統に縛られることを嫌い、気の赴くままにどこへでも飛び出していける人。 | AM47: 辛 | AN47: 卯
B48: 印綬 | C48: 学習 | P48: 印綬 | Q48: 知性の星 | R48: 習得本能 | S48: 常にインプットし、同時にアウトプットもし続ける。 | T48: 【プライド高き学究人間】 | U48: 理知的で冷静であり情愛も厚いが、やや決断力が乏しい。プライドが高く自己中心的だが反省心が強く人格的生き方をする。 | AM48: 辛 | AN48: 巳
AM49: 辛 | AN49: 未
AM50: 壬 | AN50: 戌
A51: 比肩 | B51: 活動 | C51: 2026年行動アドバイス； 新たな価値を見出す 今年のテーマ：実行・積極的・独立・計画・体調万全・人の上に立つ機会が増える。 成功キーワード：先送りせず決断力でチャンスを生み出せ この時期は、何事にも積極的に出て行く姿勢を取り、考えや気持ちを押し出していくのが良いでしょう。伸びようという意欲が環境の変化にも対応させてくれるはずです。1月~4月中には、終わらせることを終わらせ、進めるべきこと、方針を決める。先ずは一人で始めて、腑に落ちてから周囲を巻き込んでいきましょう。小さなことから取り掛かる。8月に新たな決断。ここで始められていれば勝ち！11月は8月の行動の結果が生む。11月の結果を見て修正を行う。未来に明るいビジョンを描きましょう。 | AM51: 壬 | AN51: 子
A52: 劫財 | B52: 浪費 | C52: 2026年行動アドバイス； ブレない軸を持つ。（考え方に関する軸、しっかりとした軸を持つ事が重要） 自分の為の時間・お金の管理・休息・協力者・細心の注意 成功キーワード：仲間(目的と価値観を共有出来る人)やチームで価値創造の掛け算を起こしていく この時期は、自己投資を心掛け、気力を充電するとき、共に夢を実現する仲間を見出し、周りの力(同じ価値観の人)を借りながら進めていく。協力者を得て強気な行動力を発揮できますが、時間とお金の無駄を改めましょう。4月中に体力の限界が来ていたら、時間効率を考えた方法に変える。8月は自分の苦手分野を一人で抱え込むのではなく、役割分担をして動く。10月に勢いを作り、11月は長期的な視野を持った選択をし、チームを構築する。11月は、内(チーム)外(協力者)の人間関係を強固にする | AM52: 壬 | AN52: 寅
A53: 食神 | B53: 調整 | C53: 2026年行動アドバイス；楽しいと感じることを優先する 成功のキーワード：新しい体験への積極的な一歩で道を拓け 精神的に安定し、将来の見通しも明るくなる時。しかし、そんな時こそ自分を見つめ直して修正点を点検しておきましょう。どうなりたいのか？だけを優先して考え、自分・自社のPR・発信をする。流れがチャンスを作り、流れに乗る。新しい事(ワクワクする事)を重視して生活すると良い時期。しがらみから自分を解放する。『ごめん、忙しくなるの』位のやんわりと断るくらいでいい。7月には、曖昧な状態をなくす。周囲への過度な気遣いを無くしていく。今は違うだけ、断ってもいつかは繋がる。8月外に向けて発信 11月に達成。11月には、未来のイメージをビジョン化する。 | AM53: 壬 | AN53: 辰
A54: 傷官 | B54: 焦燥 | C54: 2026年行動アドバイス；上昇のチャンスで巻き返す・好きを得意に得意を武器に殻を破る・自発性が必要 成功キーワード：楽を選ばず、大変さこそが最大の近道だ 選択肢が二つあったら大変な方を選ぶ。逃げ道を作らず集中(一点集中)。上昇する未来のみに意識を向ける。前向きな意識と感情のコントロールが重要。伝え方・言葉に注意。『これが出来るのは、あなたのお陰よ』と感謝の気持ちを口にする。突き抜ける勇気と思いやりの心が重要。今までの環境から力ずくで脱皮し、大胆に行動する事で可能性を模索する時。おおらかな気持ちで人と接する事で強い味方が現れるはず。 4月中に躊躇せずに選択する。8月はここで弾みをつけ、流れを作る 9月は拡がり、11月展開・拡大へ更なるチャレンジへ | AM54: 壬 | AN54: 午
A55: 偏財 | B55: 投資 | C55: 2026年行動アドバイス；人を見る目を養う。成功キーワード：社会課題の繋がる経営・ビジネスへ移行 自ら積極的に働きかけて物事が形に表れるときです。人間関係は究めて良好で、思いもよらなかったような出逢いがあるかもしれません。特に今年は、人との出逢いを大切にしてください。どのような人がこれから必要かイメージし、自分と周りのレベルアップに取り掛かりましょう。人から、教えてもらう事が重要です。4月は、自分自身の動きで流れを作る。8月は、徳のある人(隙がある周りに人が集まる人)と繋がる。9月は、自他の利益のためバランスよく動き、人脈を拡大する。11月に自分のネットワークが出来ている | AM55: 壬 | AN55: 申
A56: 正財 | B56: 成果 | C56: 2026年行動アドバイス；縁の下の力持ちを意識する。成功キーワード：ゆっくりと時間をかけカタチを造る。 去年、人の紹介や協力をしてくれた人を大切に。その人から頼まれたら、応える。全ての物事が順調に発展する時期、体力気力共に充実しているので、普段の二倍三倍と頑張って。(頑張っている方は、ほどほどに倒れない程度に頑張りましょう)収益になっているか戦略的に考える。やれるかなぁと言う不安を取り払いましょう。達成させるべきことを絞り、目標計画に沿ってじっくりと時間をかけましょう。基礎固めに時間を投資し、仕組み造りに力を入れましょう。必要な物の見極めも大事です。余力が出たら未来に投資しましょう。3月は、問題点より可能性に意識を向けて行動する。8月は、やるべきことを絞り、分散しない。十分収益として回収できている形が理想。コツコツと固い収益を積み上げる。10月完成を目指し、11月次のステージの準備に入る | AM56: 癸 | AN56: 亥
A57: 偏官 | B57: 転換 | C57: 2026年行動アドバイス；大きな視点で物事を見る。成功キーワード：新たなやり方、方法を導き、突破する。動きの激しい時、今の環境から抜け出したくなる時。動きに応じて出費も多くなりがち。収益の見込める仕事に使って抑えるべき所は抑える注意は必要。今迄できなかった事を試すには最良の年。『今年、行ける』と言う感覚は、頑張って来たからこそ！困難だと思ったら、人に教えを請い方法を変えていく。準備は、動きながら、動きの中で作る。チャレンジをしていくその中から、優先順位を絞っていく。迷ったら行動。①動く②広がる③優先順位を絞るを毎月繰り返すととんでもない所へ行ける予感。多くのチャレンジから、一つの可能性が見え未来の流れが生まれる。時には、休む事も仕事と捉えエネルギー管理をする。迅速な行動でステップアップ。8月に大きな変化を起こし、広がりと絞り込みを交互に行う。9月に手ごたえを感じられる。10月に一度修正し、優先順位を見直す。 | AM57: 癸 | AN57: 丑
A58: 正官 | B58: 完結 | C58: 2026年行動アドバイス；信頼を築き、それを基盤にし信用を築いていく。誠実である事。 成功キーワード：スピードよりも確実性を重視せよ 常に冷静に正しく清い判断が出来るときですが、目先の利益で選択をすると間違う可能性があるので気を付けましょう。社会的な発展とともに金銭的にも恵まれてくるでしょう。目先の利益にとらわれず、しっかりと信用を作っていき、10年のうち最も安定した年になるよう計画を立てて過ごしてください。信頼と責任は、コミットすることで得られます。先ず、目標を口に出して有言実行を目指しましょう。結果を得られなくても目標に近づくことが大事です。チーム・組織の未来ビジョンをみんなで話し合い夢の達成の共通を認識するのも大事。4月は、情報収集をしっかりと行い観察する。これからの方向性をじっくり考える時。8月は、未来の設計図を作り上げて、未来に対しての決断をする。この決断があることによって、10月にはチーム・組織の核となる体制を作れる。 | AM58: 癸 | AN58: 卯
A59: 偏印 | B59: 整理 | C59: 2026年行動アドバイス；動きが未来を創る。迷ったら前進。 アイディア・整理整頓・優先順位・仲間の援助・生活環境の変化。 成功キーワード：自分が前に出てリーダーシップを取る 物事の判断基準が曖昧になります。慌てたり、焦ったりは禁物。身体よりも頭が活発な時なので、発想をめぐらせると良い。考えてから動くことで物事が順調に進むはずです。新たな価値観を生む為に情報のアンテナを張りましょう。迷ったら小さく始める。考えすぎないリラックスした状態を作って、価値あるものを生み出すことを優先しましょう。アイディアを得るために、習慣を変えてみたり、外見や服装を変えてみましょう。自分の進化・成長から可能性が生まれます。全ての答えは、自分の中にある。アイディアや時間を産む為には、一回過去の物を手放していく事が必要。助言を求め、それをアイディアに繋げる。8月はなぜそう感じたのかの観察が未来に繋がる。周囲の意見をしっかり聞く事も大事。10月は、新たなステージへ 11月は過去を振り返り、進化することを考える。 | AM59: 癸 | AN59: 巳
A60: 印綬 | B60: 学習 | C60: 2026年行動アドバイス；興味と社会のニーズが重なる方向へ。社会のニーズを知る事が大事。 成功キーワード：その分野のプロフェッショナルを目指す。 すっきりしていなかった頭が霧が晴れる様に明晰になり、心身ともに明るくなる時。吸収して学ぶ姿勢が周囲から評価されます。自己成長を心がけて、今迄やってきた事をまとめる。自分の強みを明確に！自分の得意(心が惹かれる物)を見つける事がベスト。本屋さんに立ち寄って、パッと目に入った本を読む事もオススメ。10年の集大成！過去の経験が生きてくる。体験談だけでは主観が入るので、その道のプロから学ぶと広がりが生まれる。準備を整え 8月は求められ、信頼されている状態を作る。 9月には、これから来る新しいステージの準備に入る。9月の発信で11月からの評価を作る | AM60: 癸 | AN60: 未
AM61: 癸 | AN61: 酉
C62: 順行 | L62: 逆行
B63: 甲 | C63: 乙 | D63: 丙 | E63: 丁 | F63: 戊 | G63: 己 | H63: 庚 | I63: 辛 | J63: 壬 | K63: 癸 | L63: 癸 | M63: 壬 | N63: 辛 | O63: 庚 | P63: 己 | Q63: 戊 | R63: 丁 | S63: 丙 | T63: 乙
B64: 乙 | C64: 丙 | D64: 丁 | E64: 戊 | F64: 己 | G64: 庚 | H64: 辛 | I64: 壬 | J64: 癸 | K64: 甲 | L64: 甲 | M64: 癸 | N64: 壬 | O64: 辛 | P64: 庚 | Q64: 己 | R64: 戊 | S64: 丁 | T64: 丙
B65: 丙 | C65: 丁 | D65: 戊 | E65: 己 | F65: 庚 | G65: 辛 | H65: 壬 | I65: 癸 | J65: 甲 | K65: 乙 | L65: 乙 | M65: 甲 | N65: 癸 | O65: 壬 | P65: 辛 | Q65: 庚 | R65: 己 | S65: 戊 | T65: 丁
B66: 丁 | C66: 戊 | D66: 己 | E66: 庚 | F66: 辛 | G66: 壬 | H66: 癸 | I66: 甲 | J66: 乙 | K66: 丙 | L66: 丙 | M66: 乙 | N66: 甲 | O66: 癸 | P66: 壬 | Q66: 辛 | R66: 庚 | S66: 己 | T66: 戊
B67: 戊 | C67: 己 | D67: 庚 | E67: 辛 | F67: 壬 | G67: 癸 | H67: 甲 | I67: 乙 | J67: 丙 | K67: 丁 | L67: 丁 | M67: 丙 | N67: 乙 | O67: 甲 | P67: 癸 | Q67: 壬 | R67: 辛 | S67: 庚 | T67: 己
B68: 己 | C68: 庚 | D68: 辛 | E68: 壬 | F68: 癸 | G68: 甲 | H68: 乙 | I68: 丙 | J68: 丁 | K68: 戊 | L68: 戊 | M68: 丁 | N68: 丙 | O68: 乙 | P68: 甲 | Q68: 癸 | R68: 壬 | S68: 辛 | T68: 庚
B69: 庚 | C69: 辛 | D69: 壬 | E69: 癸 | F69: 甲 | G69: 乙 | H69: 丙 | I69: 丁 | J69: 戊 | K69: 己 | L69: 己 | M69: 戊 | N69: 丁 | O69: 丙 | P69: 乙 | Q69: 甲 | R69: 癸 | S69: 壬 | T69: 辛
B70: 辛 | C70: 壬 | D70: 癸 | E70: 甲 | F70: 乙 | G70: 丙 | H70: 丁 | I70: 戊 | J70: 己 | K70: 庚 | L70: 庚 | M70: 己 | N70: 戊 | O70: 丁 | P70: 丙 | Q70: 乙 | R70: 甲 | S70: 癸 | T70: 壬
B71: 壬 | C71: 癸 | D71: 甲 | E71: 乙 | F71: 丙 | G71: 丁 | H71: 戊 | I71: 己 | J71: 庚 | K71: 辛 | L71: 辛 | M71: 庚 | N71: 己 | O71: 戊 | P71: 丁 | Q71: 丙 | R71: 乙 | S71: 甲 | T71: 癸
B72: 癸 | C72: 甲 | D72: 乙 | E72: 丙 | F72: 丁 | G72: 戊 | H72: 己 | I72: 庚 | J72: 辛 | K72: 壬 | L72: 壬 | M72: 辛 | N72: 庚 | O72: 己 | P72: 戊 | Q72: 丁 | R72: 丙 | S72: 乙 | T72: 甲
A74: 甲 | B74: (きのえ)は、杉の木の様に まっすぐ大きく伸びる大樹を表します。 自分で決めたことを徹底的にやる 意志の強さを持つ リーダータイプです。 キーワード：自立・強い意志・実直・曲がったことが嫌い | C74: 甲(きのえ)は、杉の木の様にまっすぐ大きく伸びる大樹を表します。自分で決めたことを徹底的にやる意志の強さを持つリーダータイプです。 キーワード：自立・強い意志・実直・曲がったことが嫌い
A75: 乙 | B75: (きのと)は、たんぽぽの様な草花を表します。 見た目は、柔らかいが、 意志が強く 人も集まってきやすいです。 キーワード：柔軟性・協調性・多面性・集団の中で力を発揮する | C75: 乙(きのと)は、たんぽぽの様な草花を表します。見た目は柔らかいが、意志が強く、自然と人が集まる信頼を得やすい方です。 キーワード：柔軟性・協調性・多面性・集団の中で力を発揮する
A76: 丙 | B76: (ひのえ)は、太陽の光や 激しく燃え盛る炎を表します。 声が大きい方が多く よく喋り、活発で情熱的です。 キーワード：明るく温かい・公明正大・カリスマ性 | C76: 丙(ひのえ)は、太陽の光や 激しく燃え盛る炎を表します。声が大きい方が多くよく喋り、活発で情熱的です。 キーワード：明るく温かい・公明正大・カリスマ性
A77: 丁 | B77: (ひのと)は、ろうそくの明かりや 暖炉の穏やかな炎を表します。 そんな丁さんは、一人でも平気(自分時間) 傷つきやすくデリケート。綺麗な方が多いです。 キーワード：孤独・変化・不安定・周囲を巻き込む | C77: 丁(ひのと)は、ろうそくの明かりや 暖炉の穏やかな炎を表します。一人でも平気(自分時間)なタイプ。 傷つきやすくデリケート。綺麗な方が多いです。 キーワード：孤独・変化・不安定・周囲を巻き込む
A78: 戊 | B78: (つちのえ)は、山や堤防を表します。 不動の山、自分からは動かないが、人が集まる。 頼ってこられると面倒見がよく世話好き。 どんな状況でもビビらない。 キーワード：信頼・不動・どっしりとして周囲の目標になる | C78: 戊(つちのえ)は、山や堤防を表します。不動の山。自分からは動かないが、人が自然と集まります。頼ってこられると面倒見がよく世話好き。どんな状況でもビビらない方が多いです。 キーワード：信頼・不動・どっしりとして周囲の目標になる
A79: 己 | B79: (つちのと)は、養分を蓄えた畑を表します。 現実的で庶民的。 等身大で見栄を張るのが嫌。 人懐っこくモテる人が多いです。 キーワード：庶民的・バランス感覚がある・内面の複雑さ(思慮深い) | C79: 己(つちのと)は、養分を蓄えた畑を表します。現実的で庶民的。等身大で見栄を張るのが嫌。人懐っこくモテる人が多いです。 キーワード：庶民的・バランス感覚がある・内面の複雑さ(思慮深い)
A80: 庚 | B80: (かのえ)は、未だ鍛錬されていない荒金 （金鉱脈、原石、玉鋼）を表します。 玉鋼は、炎で熱され、叩いて伸ばされ、 水で固められ、鍛錬されて刀となります。 あえて、いばらの道を選び、挑戦し続ける革命家です。 キーワード：ストレート・合理的・行動的 | C80: 庚(かのえ)は、未だ鍛錬されていない荒金（金鉱脈、原石、玉鋼）を表します。玉鋼は、炎で熱され、叩いて伸ばされ、水で固められ、鍛錬されて刀となります。あえて、いばらの道を選び、挑戦し続ける革命家です。 キーワード：ストレート・合理的・行動的
A81: 辛 | B81: (かのと)は、光り輝くダイアモンドを表します。 水面に映る日の光がキラキラ綺麗な様に 周りに自分を輝かせてくれる人がいると更に魅力が開花します。 ダイアモンドに繊細なカットを施すためには鍛錬された技術が要ります。 言葉や仕草を鍛錬して、更に素敵なダイアモンドになっていきましょう。 キーワード：美意識・プライド・受動的 | C81: 辛(かのと)は、光り輝くダイアモンドを表します。水面に映る日の光がキラキラ綺麗な様に周りに自分を輝かせてくれる人がいると更に魅力が開花します。ダイアモンドに繊細なカットを施すためには鍛錬された技術が要ります。言葉や仕草を鍛錬して、更に素敵なダイアモンドになっていきましょう。 キーワード：美意識・プライド・受動的
A82: 壬 | B82: (みずのえ)は、海や大河を表します。 物事を循環する能力に長けている。 環境に左右されやすく流されやすい。 その反面どんな環境でも生きていける強さがある。 束縛が嫌い。お金に対して執着がない キーワード：流動的・自由闊達・スケールが大きい・神秘 | C82: 壬(みずのえ)は、海や大河を表します。 物事を循環する能力に長けている。環境に左右されやすく流されやすい。その反面どんな環境でも生きていける強さがある。束縛が嫌い。お金に対して執着がない キーワード：流動的・自由闊達・スケールが大きい・神秘
A83: 癸 | B83: (みずのと)は、雨、露、川などを表します。 慎重で学ぶことが好き。 厳しさの中にある優しさ(母性的) 器によって形を変えられる。 （高校・大学・職場など） キーワード：クール・寄せ集める・目立たない努力 | C83: 癸(みずのと)は、雨、露、川などを表します。慎重で学ぶことが好き。厳しさの中にある優しさ(母性的)。器（高校・大学・職場など）によって形を変えられる。 キーワード：クール・寄せ集める・目立たない努力
A89: 甲
A90: 乙
A91: 丙
A92: 丁
A93: 戊
A94: 己
A95: 庚
A96: 辛
A97: 壬
A98: 癸
A100: 絶 | C100: 【好きなこと】 自由気ままに出かけたり、自分の時間を楽しむこと。変化に応じてカンを働かせ、カッコよく対処すること。状況に応じた切り替えが速い。人を使うのがうまい。最低限のルールを伝えそれさへ守れば自由にしてよい。環境があっている。一瞬で場の空気を変えられる。得意分野には爆発的能力を発揮する。 【嫌なこと】 プライバシーに踏み込む。長話・長電話。管理・束縛など『枠』に入れること。いちいち細かく指摘されることが嫌い。 キーワード：感性・直感・気ままに～・超合理的・大企業(世間体) | Q100: 地球 | R100: 目標変化型 | S100: 応用拡大型 | T100: 右脳 | U100: メリット型 | V100: 管理型アイデアマン | W100: =A100 -> 絶
A101: 胎 | C101: 【好きなこと】 独りの時間と空間。自分しかできないことで№１を目指す。納得するまで考える。すぐメモを取りたがる。初志貫徹の精神。時系列の記憶力が高い。自己流を持っている(名前を付けたがる)。『かわってるね』『個性的だね』『格好いい』と言われると嬉しい。 【嫌なこと】 『早く！！』と急かされたり、ペースを乱されることを極端に嫌う。人まねはしたくない。臨機応変は苦手。 依頼に対しての経過報告がない。 【キーワード】：独自性・頭で勝負・ユニーク・オリジナリティ | Q101: 月 | R101: 目標直進型 | S101: 応用拡大型 | T101: 右脳 | U101: メリット型 | V101: 管理型アイデアマン | W101: =A101 -> 胎
A102: 養 | C102: 【好きなこと】 何が何でもではなく無理なく自然体でいられること。自分が安心できる環境をじっくり作り上げていくこと。好奇心旺盛(親しい人と冒険にでかける)。人の間違いを修正したくなる。 【嫌なこと】 初対面の人が苦手なので質問攻めにしてしまう(安心したい)が、緊張が長続きしないのでいつの間にか仲良くなっている。愛情が確認できないと不安になる為遠距離恋愛は×。駆け引きや裏表のある態度は苦手嘘をつかれることが嫌い(冗談が通じない場合あり)。 【キーワード】：信頼・安全性・原理・本物・探求心 | Q102: 太陽 | R102: 目標変化型 | S102: 原理原則型 | T102: 右脳 | U102: メリット型 | V102: 管理型アイデアマン | W102: =A102 -> 養
A103: 長生 | C103: 【好きなこと】 チャンスをつかみ成果・結果を出せる事。日々ゲーム。競争をすること。ギブ＆テイクの駆け引き。初対面の人ともすぐ仲良くなれる。短期決戦の勝負に強い。気配りをしながらムードを盛り上げる。明確な言葉で褒められることが好き。 【嫌なこと】 指示が明確じゃないこと。優柔不断な態度。話す時にキョロキョロされるのは嫌い。何もない状況でじっとしていることが苦手。怒られることが嫌いすぎて嘘をつく。 【キーワード】：すぐ使える・即効性・短期的・白黒はっきり・お得 | Q103: 地球 | R103: 目標直進型 | S103: 応用拡大型 | T103: 左脳 | U103: メリット型 | V103: 現場型攻め | W103: =A103 -> 長生
A104: 沐浴 | C104: 【好きなこと】 好奇心旺盛になんでもチャレンジすること。大きな夢と希望を持って、自分を大きくしていくこと。話の呑み込みが早い。同時進行にあれこれできる。常に大勢の中心でいたい。超プラス思考。軽はずみ的な人の好さがある。きれいに盛り付けられたお肉が好き。大きな数字には強く細かい数字には弱い。 【嫌なこと】 待たされること。ダラダラした態度をとられること。他人の悪口や文句を言うこと。(沢山の人に気を遣うから)大衆浴場が嫌。ぐちゃっとしたものが嫌。 【キーワード】：Big・Power・今すぐ・成功・世界的視野 | Q104: 太陽 | R104: 目標変化型 | S104: 応用拡大型 | T104: 左脳 | U104: メリット型 | V104: 現場型攻め | W104: =A104 -> 沐浴
A105: 冠帯 | C105: 【好きなこと】 周りより一足先に、新しい情報や機材を持つ事。スマートにリーダーシップをとり、まとめていくこと。気を遣われると嬉しい。話し合いから自分のペースを作り。いつの間にか自分の話をしている。日々成長していることが分かること。新しい物を買うと気分が上がる。 【嫌なこと】 初対面でのぞんざいな言葉遣い。強引な行動。人前で叱られること。割と傷つきやすい。 【キーワード】：最新の～・スマート・新技術・かっこいい・日々精進 | Q105: 月 | R105: 目標直進型 | S105: 原理原則型 | T105: 左脳 | U105: メリット型 | V105: 現場型攻め | W105: =A105 -> 冠帯
A106: 建禄 | C106: 【好きなこと】 さりげなく、やるべきことをやって周りを驚かせること。人前で身銭をパッと使うなどカッコつけて見せる事。VIP待遇。仲間で仕事をすること。おにぎりが好き。決して弱音を吐かない。その道の先生を目指すこと。 【嫌なこと】 愚痴や手抜きを見せられること。きちんとした対応態度を取らないこと。プライドを傷つけられること。真面目なので咄嗟の応用が苦手。甘えん坊なのに甘え下手。 【キーワード】：確実性・きっちり・完璧主義・絶対・社会的権威 | Q106: 太陽 | R106: 目標変化型 | S106: 応用拡大型 | T106: 左脳 | U106: デメリット型 | V106: 管理型ムードメーカー | W106: =A106 -> 建禄
A107: 帝旺 | C107: 【好きなこと】 人に対して常に公平でいること。全体を見渡せる席が好き(座る場所が決まっている) 初志貫徹(納得して決めると徹底的にやる)。気に入ると大人買いする 笑いながらキツイ一言が言える。スキンシップが好き(心を許す人とだけ) 【嫌なこと】 全体像がつかめないと嫌。誠心誠意のない行動(不義理を嫌う) 神経を逆なでするような言い方。指示されたくない。人によって態度を変える人が嫌い 【キーワード】：バランス・一歩一歩・誠意・納得・自分に負けない・一問一答 | Q107: 地球 | R107: 目標直進型 | S107: 応用拡大型 | T107: 左脳 | U107: デメリット型 | V107: 管理型ムードメーカー | W107: =A107 -> 帝旺
...

Sheet 原本
G2: 生年月日・生まれた時間 | L2: 出生地 | M2: 年齢 | N2: 性別
C3: 氏名 | D3: ［氏名］ | Q3: 五行判定
H4: A 元命式のみ | Q4: =IF($E$7="","",VLOOKUP(E7,計算用!$P$28:$Q$37,2,FALSE)) | R4: =IF($E$7="","",VLOOKUP($Q$4,計算用!$S$28:$W$32,2,FALSE)) | S4: =IF($E$7="","",VLOOKUP($Q$4,計算用!$S$28:$W$32,3,FALSE)) | T4: =IF($E$7="","",VLOOKUP($Q$4,計算用!$S$28:$W$32,4,FALSE)) | U4: =IF($E$7="","",VLOOKUP($Q$4,計算用!$S$28:$W$32,5,FALSE))
D6: 時柱 | E6: 日柱 | F6: 月柱 | G6: 年柱 | K6: ［点数］ | R6: 時柱 | S6: 日柱 | T6: 月柱 | U6: 年柱 | V6: 合計
C7: 干支 | Q7: 木 | V7: =SUM(R7:U7) -> 0
I8: ［点数］ | M8: ［点数］ | Q8: 火 | V8: =SUM(R8:U8) -> 0
C9: 蔵干 | Q9: 土 | V9: =SUM(R9:U9) -> 0
C10: 通変星 | Q10: 金 | V10: =SUM(R10:U10) -> 0
C11: 蔵干通変星 | Q11: 水 | V11: =SUM(R11:U11) -> 0
C12: 十二運星 | J12: ［点数］ | L12: ［点数］
C13: 空亡(天中殺)
N14: ※空亡：素直・反省・感謝を忘れずに。自我を無理に通すより流れに乗るとき。可能性を信じること。
C15: 今年の影響：木 8 → 9（+1）、水 8 → 12（+4）
C16: 大運の影響：木 9 → 8（-1）、火 4 → 6（+2）
C17: 差分・グラフの数値は配置確認用です。
B18: ●特殊な命式
C19: ［判定名］ | E19: ［正式な判定説明］ | Q19: ※傷官：細かいところに気が付く、プライドが高い、口の禍が起こりやすい。
C20: ［判定名］ | E20: ［正式な判定説明］
C21: ［判定名］ | E21: ［正式な判定説明］
C22: ［判定名］ | E22: ［正式な判定説明］
C23: ［判定名］ | E23: ［正式な判定説明］
C24: ［判定名］ | E24: ［正式な判定説明］
B25: ●干支から読み取れるもの
B29: ●通変星・蔵干通変星から読み取れるもの
C30: 幼年期 | I30: 青年期
C32: 成熟期 | I32: 老年期
Q33: 用神判定 | R33: =IF($E$7="","",VLOOKUP($E$7,計算用!$P$28:$Q$37,2,FALSE))
B34: ●本来の自分らしさ 現在段階：［人生段階］ ［通変星 × 蔵干通変星］
B36: ●十二運星から読み取れる性格
C37: 意思決定の時の自分（年柱） | I37: 初対面の人と会った時の自分（月柱）
C39: ［十二運星名］ キーワード：［正式キーワード］ | I39: ［十二運星名］ キーワード：［正式キーワード］
C40: 一人の時の自分（日柱） | I40: どんな老後を過ごしたいか（時柱）
C42: ［十二運星名］ キーワード：［正式キーワード］ | I42: ［十二運星名］ キーワード：［正式キーワード］
B43: ●考え方の傾向
C44: ＜右脳型・左脳型＞ | F44: ＜メリット・デメリット＞ | I44: ＜仕事4分類＞
C49: ＜目標への向かい方＞
B55: ●大運
C56: ［年齢帯］ | D56: ［年齢帯］ | E56: ［年齢帯］ | F56: ［年齢帯］ | G56: ［年齢帯］ | H56: ［年齢帯］ | I56: ［年齢帯］ | J56: ［年齢帯］ | K56: ［年齢帯］ | L56: ［年齢帯］
C57: ［通変星］ | D57: ［通変星］ | E57: ［通変星］ | F57: ［通変星］ | G57: ［通変星］ | H57: ［通変星］ | I57: ［通変星］ | J57: ［通変星］ | K57: ［通変星］ | L57: ［通変星］
C58: ［干］ | D58: ［干］ | E58: ［干］ | F58: ［干］ | G58: ［干］ | H58: ［干］ | I58: ［干］ | J58: ［干］ | K58: ［干］ | L58: ［干］
C59: ［支］ | D59: ［支］ | E59: ［支］ | F59: ［支］ | G59: ［支］ | H59: ［支］ | I59: ［支］ | J59: ［支］ | K59: ［支］ | L59: ［支］
B60: ●年運 太罫線：接木運の境界（試作表示） | L60: ［対象年］ | M60: ［干］ | N60: ［支］
C61: 通変星 | E61: ［星］ | G61: 年運テーマ：［正式テーマ］
C62: 月運（2月～翌年1月） 赤い字：空亡
C63: ２月 | D63: ３月 | E63: ４月 | F63: ５月 | G63: 6月 | H63: ７月 | I63: ８月 | J63: ９月 | K63: 10月 | L63: 11月 | M63: 12月 | N63: 1月
C64: ［干］ | D64: ［干］ | E64: ［干］ | F64: ［干］ | G64: ［干］ | H64: ［干］ | I64: ［干］ | J64: ［干］ | K64: ［干］ | L64: ［干］ | M64: ［干］ | N64: ［干］
C65: ［支］ | D65: ［支］ | E65: ［支］ | F65: ［支］ | G65: ［支］ | H65: ［支］ | I65: ［支］ | J65: ［支］ | K65: ［支］ | L65: ［支］ | M65: ［支］ | N65: ［支］
C66: ［星］ | D66: ［星］ | E66: ［星］ | F66: ［星］ | G66: ［星］ | H66: ［星］ | I66: ［星］ | J66: ［星］ | K66: ［星］ | L66: ［星］ | M66: ［星］ | N66: ［星］
B67: ●総合アドバイス
Q81: 時柱 | R81: 老後の過ごし方 | S81: 希望 | T81: 理想 | U81: =IF(COUNTA($D$12:$G$12)<4,"",D12) | V81: =IF(COUNTA($D$12:$G$12)<4,"",VLOOKUP($U81,計算用!$A$100:$W$111,17,FALSE)) | W81: =IF(COUNTA($D$12:$G$12)<4,"",VLOOKUP($U81,計算用!$A$100:$W$111,18,FALSE)) | X81: =IF(COUNTA($D$12:$G$12)<4,"",VLOOKUP($U81,計算用!$A$100:$W$111,19,FALSE)) | Y81: =IF(COUNTA($D$12:$G$12)<4,"",VLOOKUP($U81,計算用!$A$100:$W$111,20,FALSE)) | Z81: =IF(COUNTA($D$12:$G$12)<4,"",VLOOKUP($U81,計算用!$A$100:$W$111,21,FALSE)) | AA81: =IF(COUNTA($D$12:$G$12)<4,"",VLOOKUP($U81,計算用!$A$100:$W$111,22,FALSE)) | AB81: 5 | AC81: =IF(COUNTA($D$12:$G$12)<4,"",VLOOKUP($U81,計算用!$A$100:$W$111,3,FALSE))
Q82: 日柱 | R82: 一人の時の自分 | S82: 本質 | T82: 目的 | U82: =IF(COUNTA($D$12:$G$12)<4,"",E12) | V82: =IF(COUNTA($D$12:$G$12)<4,"",VLOOKUP($U82,計算用!$A$100:$W$111,17,FALSE)) | W82: =IF(COUNTA($D$12:$G$12)<4,"",VLOOKUP($U82,計算用!$A$100:$W$111,18,FALSE)) | X82: =IF(COUNTA($D$12:$G$12)<4,"",VLOOKUP($U82,計算用!$A$100:$W$111,19,FALSE)) | Y82: =IF(COUNTA($D$12:$G$12)<4,"",VLOOKUP($U82,計算用!$A$100:$W$111,20,FALSE)) | Z82: =IF(COUNTA($D$12:$G$12)<4,"",VLOOKUP($U82,計算用!$A$100:$W$111,21,FALSE)) | AA82: =IF(COUNTA($D$12:$G$12)<4,"",VLOOKUP($U82,計算用!$A$100:$W$111,22,FALSE)) | AB82: 50 | AC82: =IF(COUNTA($D$12:$G$12)<4,"",VLOOKUP($U82,計算用!$A$100:$W$111,3,FALSE))
Q83: 月柱 | R83: 初対面の人との自分 | S83: 表面 | T83: 手段 | U83: =IF(COUNTA($D$12:$G$12)<4,"",F12) | V83: =IF(COUNTA($D$12:$G$12)<4,"",VLOOKUP($U83,計算用!$A$100:$W$111,17,FALSE)) | W83: =IF(COUNTA($D$12:$G$12)<4,"",VLOOKUP($U83,計算用!$A$100:$W$111,18,FALSE)) | X83: =IF(COUNTA($D$12:$G$12)<4,"",VLOOKUP($U83,計算用!$A$100:$W$111,19,FALSE)) | Y83: =IF(COUNTA($D$12:$G$12)<4,"",VLOOKUP($U83,計算用!$A$100:$W$111,20,FALSE)) | Z83: =IF(COUNTA($D$12:$G$12)<4,"",VLOOKUP($U83,計算用!$A$100:$W$111,21,FALSE)) | AA83: =IF(COUNTA($D$12:$G$12)<4,"",VLOOKUP($U83,計算用!$A$100:$W$111,22,FALSE)) | AB83: 30 | AC83: =IF(COUNTA($D$12:$G$12)<4,"",VLOOKUP($U83,計算用!$A$100:$W$111,3,FALSE))
Q84: 年柱 | R84: 意思決定 | S84: 意思 | T84: 思考 | U84: =IF(COUNTA($D$12:$G$12)<4,"",G12) | V84: =IF(COUNTA($D$12:$G$12)<4,"",VLOOKUP($U84,計算用!$A$100:$W$111,17,FALSE)) | W84: =IF(COUNTA($D$12:$G$12)<4,"",VLOOKUP($U84,計算用!$A$100:$W$111,18,FALSE)) | X84: =IF(COUNTA($D$12:$G$12)<4,"",VLOOKUP($U84,計算用!$A$100:$W$111,19,FALSE)) | Y84: =IF(COUNTA($D$12:$G$12)<4,"",VLOOKUP($U84,計算用!$A$100:$W$111,20,FALSE)) | Z84: =IF(COUNTA($D$12:$G$12)<4,"",VLOOKUP($U84,計算用!$A$100:$W$111,21,FALSE)) | AA84: =IF(COUNTA($D$12:$G$12)<4,"",VLOOKUP($U84,計算用!$A$100:$W$111,22,FALSE)) | AB84: 15 | AC84: =IF(COUNTA($D$12:$G$12)<4,"",VLOOKUP($U84,計算用!$A$100:$W$111,3,FALSE))
Q103: 左脳 | R103: 0.5 | T103: 目標変化型 | U103: 0.45 | W103: 現場型攻め | X103: 35
Q104: 右脳 | R104: 0.5 | T104: 目標直進型 | U104: 0.55 | W104: 現場型守り | X104: 0
T105: 原理原則型 | U105: 0.2 | W105: 管理型ムードメーカー | X105: 15
Q106: デメリット型 | R106: 0.15 | T106: 応用拡大型 | U106: 0.8 | W106: 管理型アイデアマン | X106: 50
Q107: メリット型 | R107: 0.85
Q116: 順行or逆行 | S116: 年中の天干を見る
Q117: 生日-節入日 | S117: 順行・逆行に注意
Q118: ÷3 | R118: =IF(OR($F$7="",$R$117="",$R$116=""),"",ROUND(R117/3,0))
Q119: 年代マーカー処理用 | R119: 0 | S119: =IF(OR($F$7="",$R$117="",$R$116=""),"",IF(R118<>0,R118,10)) | T119: =IF(OR($F$7="",$R$117="",$R$116=""),"",S119+10) | U119: =IF(OR($F$7="",$R$117="",$R$116=""),"",T119+10) | V119: =IF(OR($F$7="",$R$117="",$R$116=""),"",U119+10) | W119: =IF(OR($F$7="",$R$117="",$R$116=""),"",V119+10) | X119: =IF(OR($F$7="",$R$117="",$R$116=""),"",W119+10) | Y119: =IF(OR($F$7="",$R$117="",$R$116=""),"",X119+10) | Z119: =IF(OR($F$7="",$R$117="",$R$116=""),"",Y119+10) | AA119: =IF(OR($F$7="",$R$117="",$R$116=""),"",Z119+10) | AC119: =IF(COUNTA($G$3:$I$3)<3,"",AA119+10)
Q129: 空亡判定 | R129: =LEFT(E13,1) | S129: =RIGHT(E13,1)
B160: ●運気を上げるために取り入れるもの・気を付けること
C161: 命式 | F161: 用神
C162: 本質
C163: 運気上昇
N164: ※用神：日干を中心にした十干のバランス、対運の影響など、運勢を上昇させるための重要な因子。
